README.md
neo4j_api/__init__.py
neo4j_api/__main__.py
neo4j_api/cli.py
pyproject.toml
neo4j_api-0.1.0.dist-info/entry_points.txt
neo4j_api-0.1.0.dist-info/LICENSE
neo4j_api-0.1.0.dist-info/WHEEL
neo4j_api-0.1.0.dist-info/METADATA
neo4j_api-0.1.0.dist-info/RECORD
