Metadata-Version: 2.1
Name: neo4j-api
Version: 0.1.0
Summary: A Neo4j API in Python with FastAPI.
Home-page: https://github.com/pawamoy/neo4j-api
License: ISC
Author: Timothée Mazzucotelli
Author-email: pawamoy@pm.me
Requires-Python: >=3.6,<4.0
Classifier: License :: OSI Approved
Classifier: Programming Language :: Python :: 3
Classifier: Programming Language :: Python :: 3.6
Classifier: Programming Language :: Python :: 3.7
Classifier: Programming Language :: Python :: 3.8
Project-URL: Repository, https://github.com/pawamoy/neo4j-api
